flair/__init__.py
flair/data.py
flair/embeddings.py
flair/file_utils.py
flair/nn.py
flair/setup.py
flair/training_utils.py
flair/models/__init__.py
flair/models/language_model.py
flair/models/text_classification_model.py
flairstreamlined-1.1.dist-info/LICENSE
flairstreamlined-1.1.dist-info/METADATA
flairstreamlined-1.1.dist-info/WHEEL
flairstreamlined-1.1.dist-info/top_level.txt
flairstreamlined-1.1.dist-info/RECORD
