Metadata-Version: 2.1
Name: flairstreamlined
Version: 1.1
Summary: streamlined version of flair to use with aws lambda
Home-page: UNKNOWN
License: MIT
Platform: UNKNOWN
Classifier: Programming Language :: Python :: 3.6
Classifier: License :: OSI Approved :: MIT License
Classifier: Operating System :: OS Independent
Requires-Python: >3.6
Requires-Dist: torch
Requires-Dist: requests
Requires-Dist: segtok
Requires-Dist: gensim
Requires-Dist: tqdm
